{
  "village": {
    "name": "Village The Soul of India",
    "location": {
      "address1": "372 S Broadway",
      "city": "Hicksville",
      "state": "NY",
      "zip_code": "11801"
    },
    "phone": "+1 516-822-1222",
    "rating": 4.5,
    "price": "$$",
    "menu_items": [
      {
        "name": "Chicken Tikka Masala",
        "price": 16.99
      },
      {
        "name": "Butter Chicken",
        "price": 17.99
      },
      {
        "name": "Vegetable Biryani",
        "price": 14.99
      },
      {
        "name": "Garlic Naan",
        "price": 3.99
      },
      {
        "name": "Dal Makhani",
        "price": 13.99
      }
    ]
  },
  "nearby_restaurants": [
    {
      "name": "Curry Club",
      "location": {
        "address1": "10 Sample St",
        "city": "Hicksville"
      },
      "rating": 4.3,
      "price": "$$",
      "menu_items": [
        {
          "name": "Chicken Tikka Masala",
          "price": 17.99
        },
        {
          "name": "Butter Chicken",
          "price": 18.99
        },
        {
          "name": "Vegetable Biryani",
          "price": 15.99
        },
        {
          "name": "Garlic Naan",
          "price": 4.49
        }
      ]
    },
    {
      "name": "Taste of India",
      "location": {
        "address1": "20 Test Ave",
        "city": "Hicksville"
      },
      "rating": 4.4,
      "price": "$$",
      "menu_items": [
        {
          "name": "Chicken Tikka Masala",
          "price": 16.49
        },
        {
          "name": "Butter Chicken",
          "price": 17.49
        },
        {
          "name": "Vegetable Biryani",
          "price": 14.49
        },
        {
          "name": "Garlic Naan",
          "price": 3.99
        },
        {
          "name": "Dal Makhani",
          "price": 12.99
        }
      ]
    },
    {
      "name": "Mumbai Spice",
      "location": {
        "address1": "30 Mock Rd",
        "city": "Hicksville"
      },
      "rating": 4.2,
      "price": "$$",
      "menu_items": [
        {
          "name": "Chicken Tikka Masala",
          "price": 18.99
        },
        {
          "name": "Butter Chicken",
          "price": 19.99
        },
        {
          "name": "Vegetable Biryani",
          "price": 16.99
        },
        {
          "name": "Garlic Naan",
          "price": 4.99
        },
        {
          "name": "Dal Makhani",
          "price": 14.99
        }
      ]
    }
  ],
  "weather": {
    "temperature_f": 44.6,
    "is_raining": true,
    "description": "moderate rain"
  },
  "busy_status": {
    "current_popularity": 75,
    "usual_popularity": 50,
    "is_busy": true
  },
  "price_predictions": [
    {
      "item": "Chicken Tikka Masala",
      "current_price": 16.99,
      "predicted_price": 18.963499999999996,
      "price_difference": 1.9734999999999978
    },
    {
      "item": "Butter Chicken",
      "current_price": 17.99,
      "predicted_price": 20.1135,
      "price_difference": 2.1235
    },
    {
      "item": "Vegetable Biryani",
      "current_price": 14.99,
      "predicted_price": 16.6635,
      "price_difference": 1.6734999999999989
    },
    {
      "item": "Garlic Naan",
      "current_price": 3.99,
      "predicted_price": 4.5885,
      "price_difference": 0.5984999999999996
    },
    {
      "item": "Dal Makhani",
      "current_price": 13.99,
      "predicted_price": 14.9385,
      "price_difference": 0.9484999999999992
    }
  ]
}